craftlink/__init__.py
craftlink/bot.py
craftlink/command.py
craftlink/console.py
craftlink/constants.py
craftlink-1.0.1.dist-info/entry_points.txt
craftlink-1.0.1.dist-info/METADATA
craftlink-1.0.1.dist-info/WHEEL
craftlink-1.0.1.dist-info/RECORD
