Metadata-Version: 2.1
Name: craftlink
Version: 1.0.1
Summary: A Discord bot to control a Minecraft Bedrock server remotely.
License: MIT
Author: LamerLink
Author-email: 36551116+LamerLink@users.noreply.github.com
Requires-Python: >=3.9,<4.0
Classifier: License :: OSI Approved :: MIT License
Classifier: Programming Language :: Python :: 3
Classifier: Programming Language :: Python :: 3.9
Classifier: Programming Language :: Python :: 3.10
Classifier: Programming Language :: Python :: 3.11
Requires-Dist: discord-py (>=2.3.2,<3.0.0)
Requires-Dist: python-dotenv (>=1.0.0,<2.0.0)
